sr/__init__.py
sr/code.py
sr/decode.py
sr/image.py
sr/message.py
sr/sr.py
srcode-0.0.1.dist-info/LICENSE
srcode-0.0.1.dist-info/METADATA
srcode-0.0.1.dist-info/WHEEL
srcode-0.0.1.dist-info/entry_points.txt
srcode-0.0.1.dist-info/top_level.txt
srcode-0.0.1.dist-info/RECORD
